hilbert_toolkit/__init__.py
hilbert_toolkit/_version.py
hilbert_toolkit/dft.py
hilbert_toolkit/estimators.py
hilbert_toolkit/metrics.py
hilbert_toolkit/mlhilbert.py
hilbert_toolkit/synthdata.py
hilbert_toolkit/utils.py
hilbert_toolkit/wavelet.py
hilbert_toolkit/tests/__init__.py
hilbert_toolkit/tests/test_dft.py
hilbert_toolkit/tests/test_synthdata.py
hilbert_toolkit/tests/test_utils.py
hilbert_toolkit/tests/test_wavelet.py
hilbert_toolkit-0.1.4.dist-info/LICENSE.md
hilbert_toolkit-0.1.4.dist-info/METADATA
hilbert_toolkit-0.1.4.dist-info/WHEEL
hilbert_toolkit-0.1.4.dist-info/top_level.txt
hilbert_toolkit-0.1.4.dist-info/RECORD
